materials_commons/__init__.py
materials_commons/version.py
materials_commons/api/Directory.py
materials_commons/api/EtlMetadata.py
materials_commons/api/Experiment.py
materials_commons/api/File.py
materials_commons/api/GlobusDownloadRequest.py
materials_commons/api/GlobusUploadRequest.py
materials_commons/api/GlobusUploadStatus.py
materials_commons/api/Process.py
materials_commons/api/Project.py
materials_commons/api/Sample.py
materials_commons/api/Template.py
materials_commons/api/User.py
materials_commons/api/__init__.py
materials_commons/api/api.py
materials_commons/api/base.py
materials_commons/api/bulk_file_uploader.py
materials_commons/api/config.py
materials_commons/api/for_testing_backend.py
materials_commons/api/make_objects.py
materials_commons/api/mc_object_utility.py
materials_commons/api/measurement.py
materials_commons/api/property.py
materials_commons/api/remote.py
materials_commons/api/top_level_api_functions.py
materials_commons/cli/__init__.py
materials_commons/cli/clone.py
materials_commons/cli/down.py
materials_commons/cli/expt.py
materials_commons/cli/functions.py
materials_commons/cli/init.py
materials_commons/cli/list_objects.py
materials_commons/cli/ls.py
materials_commons/cli/parser.py
materials_commons/cli/proc.py
materials_commons/cli/proj.py
materials_commons/cli/remote.py
materials_commons/cli/samp.py
materials_commons/cli/templates.py
materials_commons/cli/up.py
materials_commons/etl/__init__.py
materials_commons/etl/compare_spreadsheets.py
materials_commons/etl/old_input_spreadsheet.py
materials_commons/etl/old_output_spreadsheet.py
materials_commons/etl/project_walker.py
materials_commons/etl/template2xlsx.py
materials_commons/etl/xlsxt.py
materials_commons/etl/common/__init__.py
materials_commons/etl/common/meta_data_verify.py
materials_commons/etl/common/metadata.py
materials_commons/etl/common/process_file_util.py
materials_commons/etl/common/util.py
materials_commons/etl/common/worksheet_data.py
materials_commons-0.9.1.dist-info/LICENSE
materials_commons-0.9.1.dist-info/METADATA
materials_commons-0.9.1.dist-info/WHEEL
materials_commons-0.9.1.dist-info/top_level.txt
materials_commons-0.9.1.dist-info/RECORD
