Metadata-Version: 2.1
Name: materials-commons
Version: 0.9.1
Summary: The Materials Commons tool set
Home-page: https://materials-commons.github.io/python-api/
Author: Materials Commons development team
Author-email: materials-commons-authors@umich.edu
License: MIT
Keywords: materials science mc lift prisms
Platform: UNKNOWN
Classifier: Development Status :: 3 - Alpha
Classifier: Intended Audience :: Developers
Classifier: Intended Audience :: Science/Research
Classifier: Topic :: Scientific/Engineering :: Information Analysis
Classifier: License :: OSI Approved :: MIT License
Classifier: Programming Language :: Python :: 2
Classifier: Programming Language :: Python :: 2.7
Classifier: Programming Language :: Python :: 3
Classifier: Programming Language :: Python :: 3.6
Requires-Dist: python-magic
Requires-Dist: requests
Requires-Dist: rethinkdb
Requires-Dist: pathlib (>=1.0.1)
Requires-Dist: numpy
Requires-Dist: pathlib
Requires-Dist: pathlib2
Requires-Dist: openpyxl
Requires-Dist: xlsxwriter
Requires-Dist: urllib3
Requires-Dist: pandas (>=0.21.0)
Requires-Dist: tabulate (>=0.8.1)
Requires-Dist: sortedcontainers (>=1.5.7)
